{
  "query": "SELECT * FROM servicos_execucao ORDER BY id DESC LIMIT 20;",
  "command": "mysql --batch --raw --column-names --default-character-set=utf8mb4 --host gateway02.us-east-1.prod.aws.tidbcloud.com --port 4000 --user 3WG3DCJNDgKq1ck.d12df11ceaba --database axWmxYbCBHHB5ETKSgA95A --execute SELECT * FROM servicos_execucao ORDER BY id DESC LIMIT 20;",
  "rows": [
    {
      "id": "210001",
      "eventoId": "90008",
      "formandoId": "90001",
      "tipoServico": "make_formando",
      "fornecedorId": "158",
      "quantidade": "1",
      "valorUnitario": "1815",
      "valorTotal": "1815",
      "fluxo": "pagar",
      "dataRealizacao": "NULL",
      "observacao": "NULL",
      "createdAt": "2025-12-12 16:56:07",
      "updatedAt": "2025-12-12 16:56:07"
    },
    {
      "id": "180008",
      "eventoId": "90008",
      "formandoId": "90001",
      "tipoServico": "cabelo_combinado",
      "fornecedorId": "NULL",
      "quantidade": "2",
      "valorUnitario": "1400",
      "valorTotal": "2800",
      "fluxo": "receber",
      "dataRealizacao": "NULL",
      "observacao": "NULL",
      "createdAt": "2025-12-12 15:58:46",
      "updatedAt": "2025-12-12 15:58:46"
    },
    {
      "id": "180007",
      "eventoId": "90008",
      "formandoId": "90001",
      "tipoServico": "cabelo_simples",
      "fornecedorId": "NULL",
      "quantidade": "2",
      "valorUnitario": "800",
      "valorTotal": "1600",
      "fluxo": "receber",
      "dataRealizacao": "NULL",
      "observacao": "NULL",
      "createdAt": "2025-12-12 15:58:45",
      "updatedAt": "2025-12-12 15:58:45"
    },
    {
      "id": "180006",
      "eventoId": "90008",
      "formandoId": "90001",
      "tipoServico": "make_familia",
      "fornecedorId": "158",
      "quantidade": "1",
      "valorUnitario": "3000",
      "valorTotal": "3000",
      "fluxo": "receber",
      "dataRealizacao": "NULL",
      "observacao": "NULL",
      "createdAt": "2025-12-12 15:58:45",
      "updatedAt": "2025-12-12 15:58:45"
    },
    {
      "id": "180005",
      "eventoId": "90008",
      "formandoId": "90001",
      "tipoServico": "make_formando",
      "fornecedorId": "158",
      "quantidade": "1",
      "valorUnitario": "3080",
      "valorTotal": "3080",
      "fluxo": "pagar",
      "dataRealizacao": "NULL",
      "observacao": "NULL",
      "createdAt": "2025-12-12 15:58:45",
      "updatedAt": "2025-12-12 15:58:45"
    },
    {
      "id": "180004",
      "eventoId": "90008",
      "formandoId": "90001",
      "tipoServico": "cabelo_combinado",
      "fornecedorId": "NULL",
      "quantidade": "2",
      "valorUnitario": "1400",
      "valorTotal": "2800",
      "fluxo": "receber",
      "dataRealizacao": "NULL",
      "observacao": "NULL",
      "createdAt": "2025-12-12 15:58:44",
      "updatedAt": "2025-12-12 15:58:44"
    },
    {
      "id": "180003",
      "eventoId": "90008",
      "formandoId": "90001",
      "tipoServico": "cabelo_simples",
      "fornecedorId": "NULL",
      "quantidade": "2",
      "valorUnitario": "800",
      "valorTotal": "1600",
      "fluxo": "receber",
      "dataRealizacao": "NULL",
      "observacao": "NULL",
      "createdAt": "2025-12-12 15:58:44",
      "updatedAt": "2025-12-12 15:58:44"
    },
    {
      "id": "180002",
      "eventoId": "90008",
      "formandoId": "90001",
      "tipoServico": "make_familia",
      "fornecedorId": "158",
      "quantidade": "1",
      "valorUnitario": "3000",
      "valorTotal": "3000",
      "fluxo": "receber",
      "dataRealizacao": "NULL",
      "observacao": "NULL",
      "createdAt": "2025-12-12 15:58:44",
      "updatedAt": "2025-12-12 15:58:44"
    },
    {
      "id": "180001",
      "eventoId": "90008",
      "formandoId": "90001",
      "tipoServico": "make_formando",
      "fornecedorId": "158",
      "quantidade": "1",
      "valorUnitario": "3080",
      "valorTotal": "3080",
      "fluxo": "pagar",
      "dataRealizacao": "NULL",
      "observacao": "NULL",
      "createdAt": "2025-12-12 15:58:43",
      "updatedAt": "2025-12-12 15:58:43"
    },
    {
      "id": "150005",
      "eventoId": "90008",
      "formandoId": "90001",
      "tipoServico": "cabelo_combinado",
      "fornecedorId": "NULL",
      "quantidade": "1",
      "valorUnitario": "1400",
      "valorTotal": "1400",
      "fluxo": "receber",
      "dataRealizacao": "NULL",
      "observacao": "NULL",
      "createdAt": "2025-12-12 15:22:43",
      "updatedAt": "2025-12-12 15:22:43"
    },
    {
      "id": "150004",
      "eventoId": "90008",
      "formandoId": "90001",
      "tipoServico": "cabelo_simples",
      "fornecedorId": "NULL",
      "quantidade": "2",
      "valorUnitario": "800",
      "valorTotal": "1600",
      "fluxo": "receber",
      "dataRealizacao": "NULL",
      "observacao": "NULL",
      "createdAt": "2025-12-12 15:22:42",
      "updatedAt": "2025-12-12 15:22:42"
    },
    {
      "id": "150003",
      "eventoId": "90008",
      "formandoId": "90001",
      "tipoServico": "make_formando",
      "fornecedorId": "158",
      "quantidade": "1",
      "valorUnitario": "3080",
      "valorTotal": "3080",
      "fluxo": "pagar",
      "dataRealizacao": "NULL",
      "observacao": "NULL",
      "createdAt": "2025-12-12 15:22:42",
      "updatedAt": "2025-12-12 15:22:42"
    },
    {
      "id": "150002",
      "eventoId": "90008",
      "formandoId": "90001",
      "tipoServico": "make_familia",
      "fornecedorId": "158",
      "quantidade": "4",
      "valorUnitario": "3000",
      "valorTotal": "12000",
      "fluxo": "receber",
      "dataRealizacao": "NULL",
      "observacao": "NULL",
      "createdAt": "2025-12-12 15:22:42",
      "updatedAt": "2025-12-12 15:22:42"
    },
    {
      "id": "150001",
      "eventoId": "90008",
      "formandoId": "90001",
      "tipoServico": "make_formando",
      "fornecedorId": "158",
      "quantidade": "1",
      "valorUnitario": "3080",
      "valorTotal": "3080",
      "fluxo": "pagar",
      "dataRealizacao": "NULL",
      "observacao": "NULL",
      "createdAt": "2025-12-12 15:21:25",
      "updatedAt": "2025-12-12 15:21:25"
    },
    {
      "id": "120001",
      "eventoId": "90008",
      "formandoId": "90001",
      "tipoServico": "make_formando",
      "fornecedorId": "18",
      "quantidade": "1",
      "valorUnitario": "1815",
      "valorTotal": "1815",
      "fluxo": "pagar",
      "dataRealizacao": "NULL",
      "observacao": "NULL",
      "createdAt": "2025-12-11 23:52:24",
      "updatedAt": "2025-12-11 23:52:24"
    },
    {
      "id": "90002",
      "eventoId": "90008",
      "formandoId": "90003",
      "tipoServico": "make_formando",
      "fornecedorId": "158",
      "quantidade": "1",
      "valorUnitario": "3080",
      "valorTotal": "3080",
      "fluxo": "pagar",
      "dataRealizacao": "NULL",
      "observacao": "NULL",
      "createdAt": "2025-12-11 15:47:06",
      "updatedAt": "2025-12-11 15:47:06"
    },
    {
      "id": "90001",
      "eventoId": "90008",
      "formandoId": "90002",
      "tipoServico": "make_formando",
      "fornecedorId": "158",
      "quantidade": "1",
      "valorUnitario": "3080",
      "valorTotal": "3080",
      "fluxo": "pagar",
      "dataRealizacao": "NULL",
      "observacao": "NULL",
      "createdAt": "2025-12-11 15:46:03",
      "updatedAt": "2025-12-11 15:46:03"
    },
    {
      "id": "60002",
      "eventoId": "90008",
      "formandoId": "90001",
      "tipoServico": "make_formando",
      "fornecedorId": "158",
      "quantidade": "1",
      "valorUnitario": "1815",
      "valorTotal": "1815",
      "fluxo": "pagar",
      "dataRealizacao": "NULL",
      "observacao": "NULL",
      "createdAt": "2025-12-11 15:38:12",
      "updatedAt": "2025-12-11 15:38:12"
    },
    {
      "id": "60001",
      "eventoId": "90008",
      "formandoId": "90001",
      "tipoServico": "make_formando",
      "fornecedorId": "158",
      "quantidade": "1",
      "valorUnitario": "1815",
      "valorTotal": "1815",
      "fluxo": "pagar",
      "dataRealizacao": "NULL",
      "observacao": "NULL",
      "createdAt": "2025-12-11 15:38:12",
      "updatedAt": "2025-12-11 15:38:12"
    },
    {
      "id": "30001",
      "eventoId": "90008",
      "formandoId": "90001",
      "tipoServico": "make_formando",
      "fornecedorId": "18",
      "quantidade": "1",
      "valorUnitario": "1815",
      "valorTotal": "1815",
      "fluxo": "pagar",
      "dataRealizacao": "NULL",
      "observacao": "NULL",
      "createdAt": "2025-12-11 13:27:01",
      "updatedAt": "2025-12-11 13:27:01"
    }
  ],
  "messages": [],
  "stdout": "id\teventoId\tformandoId\ttipoServico\tfornecedorId\tquantidade\tvalorUnitario\tvalorTotal\tfluxo\tdataRealizacao\tobservacao\tcreatedAt\tupdatedAt\n210001\t90008\t90001\tmake_formando\t158\t1\t1815\t1815\tpagar\tNULL\tNULL\t2025-12-12 16:56:07\t2025-12-12 16:56:07\n180008\t90008\t90001\tcabelo_combinado\tNULL\t2\t1400\t2800\treceber\tNULL\tNULL\t2025-12-12 15:58:46\t2025-12-12 15:58:46\n180007\t90008\t90001\tcabelo_simples\tNULL\t2\t800\t1600\treceber\tNULL\tNULL\t2025-12-12 15:58:45\t2025-12-12 15:58:45\n180006\t90008\t90001\tmake_familia\t158\t1\t3000\t3000\treceber\tNULL\tNULL\t2025-12-12 15:58:45\t2025-12-12 15:58:45\n180005\t90008\t90001\tmake_formando\t158\t1\t3080\t3080\tpagar\tNULL\tNULL\t2025-12-12 15:58:45\t2025-12-12 15:58:45\n180004\t90008\t90001\tcabelo_combinado\tNULL\t2\t1400\t2800\treceber\tNULL\tNULL\t2025-12-12 15:58:44\t2025-12-12 15:58:44\n180003\t90008\t90001\tcabelo_simples\tNULL\t2\t800\t1600\treceber\tNULL\tNULL\t2025-12-12 15:58:44\t2025-12-12 15:58:44\n180002\t90008\t90001\tmake_familia\t158\t1\t3000\t3000\treceber\tNULL\tNULL\t2025-12-12 15:58:44\t2025-12-12 15:58:44\n180001\t90008\t90001\tmake_formando\t158\t1\t3080\t3080\tpagar\tNULL\tNULL\t2025-12-12 15:58:43\t2025-12-12 15:58:43\n150005\t90008\t90001\tcabelo_combinado\tNULL\t1\t1400\t1400\treceber\tNULL\tNULL\t2025-12-12 15:22:43\t2025-12-12 15:22:43\n150004\t90008\t90001\tcabelo_simples\tNULL\t2\t800\t1600\treceber\tNULL\tNULL\t2025-12-12 15:22:42\t2025-12-12 15:22:42\n150003\t90008\t90001\tmake_formando\t158\t1\t3080\t3080\tpagar\tNULL\tNULL\t2025-12-12 15:22:42\t2025-12-12 15:22:42\n150002\t90008\t90001\tmake_familia\t158\t4\t3000\t12000\treceber\tNULL\tNULL\t2025-12-12 15:22:42\t2025-12-12 15:22:42\n150001\t90008\t90001\tmake_formando\t158\t1\t3080\t3080\tpagar\tNULL\tNULL\t2025-12-12 15:21:25\t2025-12-12 15:21:25\n120001\t90008\t90001\tmake_formando\t18\t1\t1815\t1815\tpagar\tNULL\tNULL\t2025-12-11 23:52:24\t2025-12-11 23:52:24\n90002\t90008\t90003\tmake_formando\t158\t1\t3080\t3080\tpagar\tNULL\tNULL\t2025-12-11 15:47:06\t2025-12-11 15:47:06\n90001\t90008\t90002\tmake_formando\t158\t1\t3080\t3080\tpagar\tNULL\tNULL\t2025-12-11 15:46:03\t2025-12-11 15:46:03\n60002\t90008\t90001\tmake_formando\t158\t1\t1815\t1815\tpagar\tNULL\tNULL\t2025-12-11 15:38:12\t2025-12-11 15:38:12\n60001\t90008\t90001\tmake_formando\t158\t1\t1815\t1815\tpagar\tNULL\tNULL\t2025-12-11 15:38:12\t2025-12-11 15:38:12\n30001\t90008\t90001\tmake_formando\t18\t1\t1815\t1815\tpagar\tNULL\tNULL\t2025-12-11 13:27:01\t2025-12-11 13:27:01\n",
  "stderr": "",
  "execution_time_ms": 66
}